MANIFEST.in
README.txt
setup.cfg
setup.py
adi/__init__.py
adi.simplestructure.egg-info/PKG-INFO
adi.simplestructure.egg-info/SOURCES.txt
adi.simplestructure.egg-info/dependency_links.txt
adi.simplestructure.egg-info/entry_points.txt
adi.simplestructure.egg-info/namespace_packages.txt
adi.simplestructure.egg-info/not-zip-safe
adi.simplestructure.egg-info/paster_plugins.txt
adi.simplestructure.egg-info/requires.txt
adi.simplestructure.egg-info/top_level.txt
adi/simplestructure/__init__.py
adi/simplestructure/configure.zcml
adi/simplestructure/tests.py
adi/simplestructure/profiles/default/metadata.xml
adi/simplestructure/profiles/default/portlets.xml
adi/simplestructure/profiles/default/viewlets.xml
docs/HISTORY.txt
docs/INSTALL.txt
docs/LICENSE.GPL
docs/LICENSE.txt