Metadata-Version: 1.0
Name: adi.simplestructure
Version: 0.4
Summary: Removes top and footer viewlets and adds portlets instead.
Home-page: http://svn.plone.org/svn/collective/
Author: Ida Ebkes
Author-email: contact@ida-ebkes.eu
License: GPL
Platform: UNKNOWN
Classifier: Framework :: Plone
Classifier: Programming Language :: Python
